LICENSE.md
README.md
pyproject.toml
src/icat_esrf_definitions/__init__.py
src/icat_esrf_definitions/hdf5_cfg.xml
src/icat_esrf_definitions.egg-info/PKG-INFO
src/icat_esrf_definitions.egg-info/SOURCES.txt
src/icat_esrf_definitions.egg-info/dependency_links.txt
src/icat_esrf_definitions.egg-info/requires.txt
src/icat_esrf_definitions.egg-info/top_level.txt
src/icat_esrf_definitions/models/__init__.py
src/icat_esrf_definitions/models/dataset.py
src/icat_esrf_definitions/models/generate.py
src/icat_esrf_definitions/models/applications/__init__.py
src/icat_esrf_definitions/models/applications/bcdi.py
src/icat_esrf_definitions/models/applications/em.py
src/icat_esrf_definitions/models/applications/fluo.py
src/icat_esrf_definitions/models/applications/holo.py
src/icat_esrf_definitions/models/applications/htxrpd.py
src/icat_esrf_definitions/models/applications/mrt.py
src/icat_esrf_definitions/models/applications/mx.py
src/icat_esrf_definitions/models/applications/ptycho.py
src/icat_esrf_definitions/models/applications/saxs.py
src/icat_esrf_definitions/models/applications/scxrd.py
src/icat_esrf_definitions/models/applications/ssx.py
src/icat_esrf_definitions/models/applications/sxdm.py
src/icat_esrf_definitions/models/applications/tomo.py
src/icat_esrf_definitions/models/applications/waxs.py
src/icat_esrf_definitions/models/base/__init__.py
src/icat_esrf_definitions/models/base/icat.py
src/icat_esrf_definitions/models/base/model.py
src/icat_esrf_definitions/models/base/nexus.py
src/icat_esrf_definitions/models/base/quantity.py
src/icat_esrf_definitions/models/base/units.py
src/icat_esrf_definitions/models/base/utils.py
src/icat_esrf_definitions/models/base_classes/__init__.py
src/icat_esrf_definitions/models/base_classes/aperture.py
src/icat_esrf_definitions/models/base_classes/external_references.py
src/icat_esrf_definitions/models/base_classes/fresnel_zone_plate.py
src/icat_esrf_definitions/models/base_classes/instrument.py
src/icat_esrf_definitions/models/base_classes/mirror.py
src/icat_esrf_definitions/models/base_classes/notes.py
src/icat_esrf_definitions/models/base_classes/process.py
src/icat_esrf_definitions/models/base_classes/sample.py
src/icat_esrf_definitions/models/base_classes/workflow.py
