Metadata-Version: 2.4
Name: icat-esrf-definitions
Version: 2.3.0
Summary: ESRF ICAT definitions
Author-email: ESRF <dau-pydev@esrf.fr>
License: # MIT License
Project-URL: Homepage, https://gitlab.esrf.fr/icat/hdf5-master-config
Project-URL: Documentation, https://icat-esrf-definitions.readthedocs.io/
Project-URL: Repository, https://gitlab.esrf.fr/icat/hdf5-master-config
Project-URL: Issues, https://gitlab.esrf.fr/icat/hdf5-master-config/issues/
Project-URL: Changelog, https://gitlab.esrf.fr/icat/hdf5-master-config/-/blob/master/CHANGELOG.md
Keywords: metadata
Classifier: Intended Audience :: Science/Research
Classifier: License :: OSI Approved :: MIT License
Classifier: Programming Language :: Python :: 3
Requires-Python: >=3.8
License-File: LICENSE.md
Requires-Dist: importlib_resources; python_version < "3.9"
Requires-Dist: typing_extensions; python_version < "3.9"
Requires-Dist: pint
Requires-Dist: pydantic
Provides-Extra: xml
Requires-Dist: xmltodict; extra == "xml"
Provides-Extra: test
Requires-Dist: icat-esrf-definitions[xml]; extra == "test"
Requires-Dist: pytest; extra == "test"
Requires-Dist: silx; extra == "test"
Provides-Extra: dev
Requires-Dist: icat-esrf-definitions[test]; extra == "dev"
Requires-Dist: pre-commit; extra == "dev"
Requires-Dist: datamodel-code-generator; extra == "dev"
Requires-Dist: tabulate; extra == "dev"
Provides-Extra: doc
Requires-Dist: icat-esrf-definitions[test]; extra == "doc"
Requires-Dist: sphinx>=4.5; extra == "doc"
Requires-Dist: sphinx-autodoc-typehints>=1.16; extra == "doc"
Requires-Dist: pydata-sphinx-theme; extra == "doc"
Dynamic: license-file
